ieeU/__init__.py
ieeU/__main__.py
ieeU/cli.py
ieeU/config.py
ieeU/constants.py
ieeU/extractor.py
ieeU/logger.py
ieeU/mineru.py
ieeU/processor.py
ieeU/vlm.py
ieeu-2.1.0.dist-info/METADATA
ieeu-2.1.0.dist-info/WHEEL
ieeu-2.1.0.dist-info/entry_points.txt
ieeu-2.1.0.dist-info/top_level.txt
ieeu-2.1.0.dist-info/RECORD
