Metadata-Version: 2.4
Name: ieeU
Version: 2.1.0
Summary: 将Markdown中的图片链接替换为VLM生成的描述性文本
Author-email: Caiyi Zheng <xiaoxiaodeyehenkeai11@gmail.com>
License: MIT
Project-URL: Homepage, https://github.com/zcyisiee/ieeU
Project-URL: Repository, https://github.com/zcyisiee/ieeU
Project-URL: Issues, https://github.com/zcyisiee/ieeU/issues
Keywords: vlm,markdown,image,description,mineru,ai
Classifier: Development Status :: 4 - Beta
Classifier: Intended Audience :: Developers
Classifier: License :: OSI Approved :: MIT License
Classifier: Programming Language :: Python :: 3
Classifier: Programming Language :: Python :: 3.8
Classifier: Programming Language :: Python :: 3.9
Classifier: Programming Language :: Python :: 3.10
Classifier: Programming Language :: Python :: 3.11
Classifier: Programming Language :: Python :: 3.12
Requires-Python: >=3.8
Requires-Dist: requests>=2.25.0
Requires-Dist: python-dateutil>=2.8.0
